eznet/__init__.py
eznet/__main__.py
eznet/check.py
eznet/data.py
eznet/example.py
eznet/logger.py
eznet/rsi.py
eznet/utils.py
eznet/verify.py
eznet/inventory/__init__.py
eznet/inventory/device/__init__.py
eznet/inventory/device/drivers/__init__.py
eznet/inventory/device/drivers/base.py
eznet/inventory/device/drivers/junos.py
eznet/inventory/device/drivers/ssh.py
eznet/inventory/device/info/__init__.py
eznet/inventory/device/info/chassis.py
eznet/inventory/device/info/interfaces.py
eznet/inventory/device/info/lldp.py
eznet/inventory/device/info/system.py
eznet/inventory/device/vars/__init__.py
eznet/inventory/device/vars/interfaces.py
eznet/inventory/device/vars/system.py
eznet/parsers/__init__.py
eznet/parsers/xml.py
eznet/scripts/__init__.py
eznet/scripts/export.py
eznet/tables/__init__.py
eznet/tables/device.py
eznet/tables/inventory.py
eznet-0.1.3.dist-info/LICENSE
eznet-0.1.3.dist-info/METADATA
eznet-0.1.3.dist-info/WHEEL
eznet-0.1.3.dist-info/entry_points.txt
eznet-0.1.3.dist-info/top_level.txt
eznet-0.1.3.dist-info/RECORD
